pyzotero_cli/__init__.py
pyzotero_cli/collection_cmds.py
pyzotero_cli/file_cmds.py
pyzotero_cli/fulltext_cmds.py
pyzotero_cli/group_cmds.py
pyzotero_cli/item_cmds.py
pyzotero_cli/search_cmds.py
pyzotero_cli/tag_cmds.py
pyzotero_cli/util_cmds.py
pyzotero_cli/utils.py
pyzotero_cli/zot_cli.py
pyzotero_cli-0.1.6.dist-info/METADATA
pyzotero_cli-0.1.6.dist-info/WHEEL
pyzotero_cli-0.1.6.dist-info/entry_points.txt
pyzotero_cli-0.1.6.dist-info/top_level.txt
pyzotero_cli-0.1.6.dist-info/RECORD
