Metadata-Version: 2.4
Name: pyzotero-cli
Version: 0.1.6
Summary: Use Zotero from the command line, e.g., for AI-assisted reference / citation management in academic writing — CLI wrapper for pyzotero
Requires-Python: >=3.10
Requires-Dist: click>=8.2.0
Requires-Dist: pyyaml>=6.0.2
Requires-Dist: pyzotero>=1.6.11
Requires-Dist: tabulate>=0.9.0
Requires-Dist: pytest>=7.0
Requires-Dist: python-dotenv>=1.1.0
Provides-Extra: dev
Requires-Dist: pytest>=8.3.5; extra == "dev"
